setup.py
ndbext/__init__.py
ndbext/property.py
ndbext.egg-info/PKG-INFO
ndbext.egg-info/SOURCES.txt
ndbext.egg-info/dependency_links.txt
ndbext.egg-info/not-zip-safe
ndbext.egg-info/top_level.txt