Metadata-Version: 1.1
Name: ndbext
Version: 0.1.3
Summary: A project to extend Google App Engine ndb properties
Home-page: https://github.com/renzon/ndbext
Author: Renzo Nuccitelli
Author-email: renzo.n@gmail.com
License: BSD
Platform: UNKNOWN
Classifier: Development Status :: 4 - Beta
Classifier: Environment :: Web Environment
Classifier: Intended Audience :: Developers
Classifier: License :: OSI Approved :: BSD License
Classifier: Operating System :: OS Independent
Classifier: Programming Language :: Python
Classifier: Framework :: Paste
